nmesh/__init__.py
nmesh/config.yml
nmesh/functional.py
nmesh/core/__init__.py
nmesh/core/functional.py
nmesh/core/nmesh.py
nmesh/pc/__init__.py
nmesh/pc/__main__.py
nmesh/pc/converter.py
nmesh/tests/__init__.py
nmesh/tests/__main__.py
nmesh/tests/test_nmesh.py
nmesh-0.1.4.dist-info/METADATA
nmesh-0.1.4.dist-info/WHEEL
nmesh-0.1.4.dist-info/top_level.txt
nmesh-0.1.4.dist-info/zip-safe
nmesh-0.1.4.dist-info/RECORD
