Metadata-Version: 2.1
Name: nmesh
Version: 0.1.4
Summary: 3D Mesh processing
Home-page: https://github.com/JeanMaximilienCadic/nmesh
Author: CADIC Jean Maximilien
Author-email: contact@cadic.jp
License: : OSI Approved :: MIT License
Keywords: 3D mesh,point cloud
Requires-Dist: pyYaml
Requires-Dist: opencv-python
Requires-Dist: scipy
Requires-Dist: trimesh
Requires-Dist: gnutools-python
Requires-Dist: numpy
Requires-Dist: matplotlib
Requires-Dist: pandas
Requires-Dist: networkx
Requires-Dist: pyglet (==1.5.27)
Requires-Dist: pmeshlab
Requires-Dist: black
